pyserrf/CV.py
pyserrf/__init__.py
pyserrf/read_data.py
pyserrf/run.py
pyserrf/serrf.py
pyserrf/test2.py
pyserrf/utils.py
pyserrf-0.2.2.dist-info/METADATA
pyserrf-0.2.2.dist-info/WHEEL
pyserrf-0.2.2.dist-info/top_level.txt
pyserrf-0.2.2.dist-info/RECORD
