Metadata-Version: 2.1
Name: pyserrf
Version: 0.2.2
Summary: Add your description here
Requires-Python: >=3.12
Requires-Dist: numpy>=2.2.0
Requires-Dist: pandas>=2.2.3
Requires-Dist: pytest>=8.3.4
Requires-Dist: scikit-learn>=1.6.0
Requires-Dist: tqdm>=4.67.1
